SpaRcle/Loader.py
SpaRcle/PySpaRcle.pyd
SpaRcle/__init__.py
SpaRcle/python37.lib
SpaRcle-0.1.4.dist-info/METADATA
SpaRcle-0.1.4.dist-info/WHEEL
SpaRcle-0.1.4.dist-info/top_level.txt
SpaRcle-0.1.4.dist-info/RECORD
