Metadata-Version: 2.1
Name: SpaRcle
Version: 0.1.4
Summary: Искусственный интеллект. Искорка :)
Home-page: UNKNOWN
Author: Monika
Author-email: rotaru5craft@gmail.com
License: MIT
Platform: UNKNOWN
